README.md
setup.py
wunderground_pws/__init__.py
wunderground_pws/api.py
wunderground_pws/exceptions.py
wunderground_pws/units.py
wunderground_pws.egg-info/PKG-INFO
wunderground_pws.egg-info/SOURCES.txt
wunderground_pws.egg-info/dependency_links.txt
wunderground_pws.egg-info/requires.txt
wunderground_pws.egg-info/top_level.txt