Metadata-Version: 2.1
Name: wunderground-pws
Version: 0.1
Summary: Small Python module for Weather Underground PWS APIs
Home-page: https://docs.marcoaceti.it/wundergroundpws/
Author: Marco Aceti
Author-email: mail@marcoaceti.it
License: MIT
Project-URL: GitHub, https://github.com/MarcoBuster/WUndergroundPWS-API
Project-URL: Documentation, https://docs.marcoaceti.it/wundergroundpws/
Platform: UNKNOWN
Classifier: License :: OSI Approved :: MIT License
Classifier: Programming Language :: Python :: 3
Classifier: Programming Language :: Python :: 3.7
